LICENSE
MANIFEST.in
README.md
setup.py
django_h5bp/__init__.py
django_h5bp/tests.py
django_h5bp.egg-info/PKG-INFO
django_h5bp.egg-info/SOURCES.txt
django_h5bp.egg-info/dependency_links.txt
django_h5bp.egg-info/requires.txt
django_h5bp.egg-info/top_level.txt
django_h5bp/static/apple-touch-icon-114x114-precomposed.png
django_h5bp/static/apple-touch-icon-144x144-precomposed.png
django_h5bp/static/apple-touch-icon-57x57-precomposed.png
django_h5bp/static/apple-touch-icon-72x72-precomposed.png
django_h5bp/static/apple-touch-icon-precomposed.png
django_h5bp/static/apple-touch-icon.png
django_h5bp/static/css/bootstrap/bootstrap-theme.css
django_h5bp/static/css/bootstrap/bootstrap-theme.min.css
django_h5bp/static/css/bootstrap/bootstrap.css
django_h5bp/static/css/bootstrap/bootstrap.min.css
django_h5bp/static/css/bootstrap/main.css
django_h5bp/static/css/classic/main.css
django_h5bp/static/css/classic/normalize.css
django_h5bp/static/css/classic/normalize.min.css
django_h5bp/static/css/responsive/main.css
django_h5bp/static/css/responsive/normalize.css
django_h5bp/static/css/responsive/normalize.min.css
django_h5bp/static/fonts/glyphicons-halflings-regular.eot
django_h5bp/static/fonts/glyphicons-halflings-regular.svg
django_h5bp/static/fonts/glyphicons-halflings-regular.ttf
django_h5bp/static/fonts/glyphicons-halflings-regular.woff
django_h5bp/static/js/bootstrap/main.js
django_h5bp/static/js/bootstrap/vendor/bootstrap.js
django_h5bp/static/js/bootstrap/vendor/bootstrap.min.js
django_h5bp/static/js/bootstrap/vendor/jquery-1.10.1.min.js
django_h5bp/static/js/bootstrap/vendor/modernizr-2.6.2-respond-1.1.0.min.js
django_h5bp/static/js/classic/main.js
django_h5bp/static/js/classic/plugins.js
django_h5bp/static/js/classic/vendor/jquery-1.10.1.min.js
django_h5bp/static/js/classic/vendor/modernizr-2.6.2.min.js
django_h5bp/static/js/responsive/main.js
django_h5bp/static/js/responsive/vendor/jquery-1.10.1.min.js
django_h5bp/static/js/responsive/vendor/modernizr-2.6.2-respond-1.1.0.min.js
django_h5bp/templates/bootstrap/bootstrap_h5bp.html
django_h5bp/templates/classic/classic_h5bp.html
django_h5bp/templates/optional/404.html
