Metadata-Version: 1.1
Name: django-h5bp
Version: 0.3.4
Summary: A simple HTML5 Boilerplate Django app that has some predefined template Blocks, useful to be extended in any application template.
Home-page: https://github.com/arruda/django-h5bp
Author: Felipe Arruda Pontes
Author-email: contato@arruda.blog.br
License: MIT License
Platform: UNKNOWN
Classifier: Environment :: Web Environment
Classifier: Framework :: Django
Classifier: Intended Audience :: Developers
Classifier: License :: OSI Approved :: MIT License
Classifier: Operating System :: OS Independent
Classifier: Programming Language :: Python
Classifier: Programming Language :: Python :: 2.6
Classifier: Programming Language :: Python :: 2.7
Classifier: Topic :: Internet :: WWW/HTTP
Classifier: Topic :: Internet :: WWW/HTTP :: Dynamic Content
